ip_safelist_middleware/__init__.py
ip_safelist_middleware/__version__.py
ip_safelist_middleware/middleware.py
ip_safelist_middleware/models.py
ip_safelist_middleware-1.2.0.dist-info/METADATA
ip_safelist_middleware-1.2.0.dist-info/WHEEL
ip_safelist_middleware-1.2.0.dist-info/licenses/LICENSE
ip_safelist_middleware-1.2.0.dist-info/RECORD
