Metadata-Version: 2.4
Name: ip-safelist-middleware
Version: 1.2.0
Summary: FastAPI Middleware for IP Address Safelisting
Project-URL: Homepage, https://github.com/gmr/ip-safelist-middleware
Project-URL: Documentation, https://gmr.github.io/ip-safelist-middleware
Project-URL: Issues, https://github.com/gmr/ip-safelist-middleware/issues
Project-URL: Changelog, https://gmr.github.io/ip-safelist-middleware/changelog/
Author-email: "Gavin M. Roy" <gavinmroy@gmail.com>
License: BSD 3-Clause License
License-File: LICENSE
Keywords: fastapi,ip,middleware,safelist,security
Classifier: Development Status :: 4 - Beta
Classifier: Framework :: FastAPI
Classifier: Intended Audience :: Developers
Classifier: License :: OSI Approved :: BSD License
Classifier: Programming Language :: Python :: 3
Classifier: Programming Language :: Python :: 3.12
Classifier: Topic :: Internet :: WWW/HTTP :: WSGI :: Middleware
Classifier: Topic :: Security
Requires-Python: >=3.12
Requires-Dist: fastapi>=0.68.0
Requires-Dist: httpx>=0.24.0
Requires-Dist: pydantic-settings
Requires-Dist: pydantic>=1.9.0
Requires-Dist: starlette>=0.14.2
Provides-Extra: dev
Requires-Dist: mypy>=1.0.0; extra == 'dev'
Requires-Dist: pyright>=1.1.396; extra == 'dev'
Requires-Dist: pytest-asyncio>=0.20.0; extra == 'dev'
Requires-Dist: pytest-cov>=4.0.0; extra == 'dev'
Requires-Dist: pytest>=7.0.0; extra == 'dev'
Requires-Dist: ruff>=0.0.260; extra == 'dev'
Provides-Extra: docs
Requires-Dist: black; extra == 'docs'
Requires-Dist: mkdocs-material<10,>9.5; extra == 'docs'
Requires-Dist: mkdocs<2,>=1.5; extra == 'docs'
Requires-Dist: mkdocstrings-python-xref<2,>=1.6; extra == 'docs'
Requires-Dist: mkdocstrings[python]<0.27,>=0.26; extra == 'docs'
